flowci/__init__.py
flowci/client.py
flowci/domain.py
python_lib_flow.ci-1.21.6.dist-info/LICENSE
python_lib_flow.ci-1.21.6.dist-info/METADATA
python_lib_flow.ci-1.21.6.dist-info/WHEEL
python_lib_flow.ci-1.21.6.dist-info/top_level.txt
python_lib_flow.ci-1.21.6.dist-info/RECORD
