Metadata-Version: 2.1
Name: python-lib-flow.ci
Version: 1.21.6
Summary: flow.ci python open api lib
Home-page: https://github.com/flowci
Author: Yang Guo
Author-email: 32008001@qq.com
License: UNKNOWN
Platform: UNKNOWN
Classifier: Development Status :: 1 - Planning
Classifier: Programming Language :: Python :: 3
Classifier: License :: OSI Approved :: Apache Software License
Classifier: Operating System :: OS Independent
Classifier: Topic :: Software Development :: Libraries
Requires-Python: >=3.6
